[
{ "name": "_eventBDTnMuons",
  "primary":
  {
    "name": "_eventBDT",
    "variable": "_eventBDT",
    "nbins": "5",
    "xlow": "0.0",
    "xhigh": "1.0",
    "axtitle": "BDT output score",
    "bins": [0.0, 0.2, 0.4, 0.6, 0.8, 1.0]
  },
  "secondary":
  {
    "name": "_nMuons",
    "variable": "_nMuons",
    "nbins": "3",
    "xlow": "-0.5",
    "xhigh": "2.5",
    "axtitle": "Number of muons in event",
    "shorttitle": "N(#mu)",
    "iscategorical": "true",
    "xlabels": ["0", "1", "2"],
    "bins": [-0.5, 0.5, 1.5, 2.5]
  }
},
{ "name": "_eventBDTnElectrons",
  "primary":
  {
    "name": "_eventBDT",
    "variable": "_eventBDT",
    "nbins": "5",
    "xlow": "0.0",
    "xhigh": "1.0",
    "axtitle": "BDT output score",
    "bins": [0.0, 0.2, 0.4, 0.6, 0.8, 1.0]
  },
  "secondary":
  {
    "name": "_nElectrons",
    "variable": "_nElectrons",
    "nbins": "3",
    "xlow": "-0.5",
    "xhigh": "2.5",
    "axtitle": "Number of electrons in event",
    "shorttitle": "N(e)",
    "iscategorical": "true",
    "xlabels": ["0", "1", "2"],
    "bins": [-0.5, 0.5, 1.5, 2.5]
  }
},
{ "name": "_eventBDTnJets",
  "primary":
  {
    "name": "_eventBDT",
    "variable": "_eventBDT",
    "nbins": "5",
    "xlow": "0.0",
    "xhigh": "1.0",
    "axtitle": "BDT output score",
    "bins": [0.0, 0.2, 0.4, 0.6, 0.8, 1.0]
  },
  "secondary":
  {
    "name": "_nJets",
    "variable": "_nJets",
    "nbins": "4",
    "xlow": "1.5",
    "xhigh": "5.5",
    "axtitle": "Number of jets",
    "shorttitle": "N(jets)",
    "iscategorical": "true",
    "xlabels": ["2", "3", "4", "5"],
    "bins": [1.5, 2.5, 3.5, 4.5, 5.5]
  }
},
{ "name": "_eventBDTnBJets",
  "primary":
  {
    "name": "_eventBDT",
    "variable": "_eventBDT",
    "nbins": "5",
    "xlow": "0.0",
    "xhigh": "1.0",
    "axtitle": "BDT output score",
    "bins": [0.0, 0.2, 0.4, 0.6, 0.8, 1.0]
  },
  "secondary":
  {
    "name": "_nBJets",
    "variable": "_nBJets",
    "nbins": "4",
    "xlow": "-0.5",
    "xhigh": "3.5",
    "axtitle": "Number of b-tagged jets",
    "shorttitle": "N(b-jets)",
    "iscategorical": "true",
    "xlabels": ["0", "1", "2", "3"],
    "bins": [-0.5, 0.5, 1.5, 2.5, 3.5]
  }
},
{ "name": "_eventBDTleptonPtLeading",
  "primary":
  {
    "name": "_eventBDT",
    "variable": "_eventBDT",
    "nbins": "5",
    "xlow": "0.0",
    "xhigh": "1.0",
    "axtitle": "BDT output score",
    "bins": [0.0, 0.2, 0.4, 0.6, 0.8, 1.0]
  },
  "secondary":
  {
    "name": "_leptonPtLeading",
    "variable": "_leptonPtLeading",
    "nbins": "4",
    "xlow": "0.0",
    "xhigh": "200.0",
    "axtitle": "Leading lepton p_{T}",
    "shorttitle": "p_{T}(l_{1})",
    "unit": "GeV",
    "bins": [0.0, 50.0, 75.0, 100.0, 200.0]
  }
},
{ "name": "_eventBDTleptonPtSubLeading",
  "primary":
  {
    "name": "_eventBDT",
    "variable": "_eventBDT",
    "nbins": "5",
    "xlow": "0.0",
    "xhigh": "1.0",
    "axtitle": "BDT output score",
    "bins": [0.0, 0.2, 0.4, 0.6, 0.8, 1.0]
  },
  "secondary":
  {
    "name": "_leptonPtSubLeading",
    "variable": "_leptonPtSubLeading",
    "nbins": "3",
    "xlow": "0.0",
    "xhigh": "100.0",
    "axtitle": "Subleading lepton p_{T}",
    "shorttitle": "p_{T}(l_{2})",
    "unit": "GeV",
    "bins": [0.0, 30.0, 50.0, 100.0]
  }
},
{ "name": "_eventBDTleptonEtaLeading",
  "primary":
  {
    "name": "_eventBDT",
    "variable": "_eventBDT",
    "nbins": "5",
    "xlow": "0.0",
    "xhigh": "1.0",
    "axtitle": "BDT output score",
    "bins": [0.0, 0.2, 0.4, 0.6, 0.8, 1.0]
  },
  "secondary":
  {
    "name": "_leptonEtaLeading",
    "variable": "_leptonEtaLeading",
    "nbins": "4",
    "xlow": "-2.5",
    "xhigh": "2.5",
    "axtitle": "Leading lepton #eta",
    "shorttitle": "#eta(l_{1})",
    "bins": [-2.5, -0.5, 0.0, 0.5, 2.5]
  }
},
{ "name": "_eventBDTleptonAbsEtaLeading",
  "primary":
  {
    "name": "_eventBDT",
    "variable": "_eventBDT",
    "nbins": "5",
    "xlow": "0.0",
    "xhigh": "1.0",
    "axtitle": "BDT output score",
    "bins": [0.0, 0.2, 0.4, 0.6, 0.8, 1.0]
  },
  "secondary":
  {
    "name": "_leptonAbsEtaLeading",
    "variable": "_leptonAbsEtaLeading",
    "nbins": "4",
    "xlow": "0.0",
    "xhigh": "2.5",
    "axtitle": "Leading lepton |#eta|",
    "shorttitle": "|#eta(l_{1})|",
    "bins": [0.0, 0.5, 1.0, 1.5, 2.5]
  }
},
{ "name": "_eventBDTleptonEtaSubLeading",
  "primary":
  {
    "name": "_eventBDT",
    "variable": "_eventBDT",
    "nbins": "5",
    "xlow": "0.0",
    "xhigh": "1.0",
    "axtitle": "BDT output score",
    "bins": [0.0, 0.2, 0.4, 0.6, 0.8, 1.0]
  },
  "secondary":
  {
    "name": "_leptonEtaSubLeading",
    "variable": "_leptonEtaSubLeading",
    "nbins": "4",
    "xlow": "-2.5",
    "xhigh": "2.5",
    "axtitle": "Subleading lepton #eta",
    "shorttitle": "#eta(l_{2})",
    "bins": [-2.5, -0.5, 0.0, 0.5, 2.5]
  }
},
{ "name": "_eventBDTleptonAbsEtaSubLeading",
  "primary":
  {
    "name": "_eventBDT",
    "variable": "_eventBDT",
    "nbins": "5",
    "xlow": "0.0",
    "xhigh": "1.0",
    "axtitle": "BDT output score",
    "bins": [0.0, 0.2, 0.4, 0.6, 0.8, 1.0]
  },
  "secondary":
  {
    "name": "_leptonAbsEtaSubLeading",
    "variable": "_leptonAbsEtaSubLeading",
    "nbins": "4",
    "xlow": "0.0",
    "xhigh": "2.5",
    "axtitle": "Subleading lepton |#eta|",
    "shorttitle": "|#eta(l_{2})|",
    "bins": [0.0, 0.5, 1.0, 1.5, 2.5]
  }
},
{ "name": "_eventBDTjetPtLeading",
  "primary":
  {
    "name": "_eventBDT",
    "variable": "_eventBDT",
    "nbins": "5",
    "xlow": "0.0",
    "xhigh": "1.0",
    "axtitle": "BDT output score",
    "bins": [0.0, 0.2, 0.4, 0.6, 0.8, 1.0]
  },
  "secondary":
  {
    "name": "_jetPtLeading",
    "variable": "_jetPtLeading",
    "nbins": "3",
    "xlow": "25.0",
    "xhigh": "300.0",
    "axtitle": "Leading jet p_{T}",
    "shorttitle": "p_{T}(jet_{1})",
    "unit": "GeV",
    "bins": [25.0, 100.0, 200.0, 300.0]
  }
},
{ "name": "_eventBDTjetEtaLeading",
  "primary":
  {
    "name": "_eventBDT",
    "variable": "_eventBDT",
    "nbins": "5",
    "xlow": "0.0",
    "xhigh": "1.0",
    "axtitle": "BDT output score",
    "bins": [0.0, 0.2, 0.4, 0.6, 0.8, 1.0]
  },
  "secondary":
  {
    "name": "_jetEtaLeading",
    "variable": "_jetEtaLeading",
    "nbins": "4",
    "xlow": "-2.5",
    "xhigh": "2.5",
    "axtitle": "Leading jet #eta",
    "shorttitle": "#eta(jet_{1})",
    "bins": [-2.5, -0.5, 0.0, 0.5, 2.5]
  }
},
{ "name": "_eventBDTjetAbsEtaLeading",
  "primary":
  {
    "name": "_eventBDT",
    "variable": "_eventBDT",
    "nbins": "5",
    "xlow": "0.0",
    "xhigh": "1.0",
    "axtitle": "BDT output score",
    "bins": [0.0, 0.2, 0.4, 0.6, 0.8, 1.0]
  },
  "secondary":
  {
    "name": "_jetAbsEtaLeading",
    "variable": "_jetAbsEtaLeading",
    "nbins": "4",
    "xlow": "0.0",
    "xhigh": "2.5",
    "axtitle": "Leading jet |#eta|",
    "shorttitle": "|#eta(jet_{1})|",
    "bins": [0.0, 0.5, 1.0, 1.5, 2.5]
  }
},
{ "name": "_eventBDTjetPtSubLeading",
  "primary":
  {
    "name": "_eventBDT",
    "variable": "_eventBDT",
    "nbins": "5",
    "xlow": "0.0",
    "xhigh": "1.0",
    "axtitle": "BDT output score",
    "bins": [0.0, 0.2, 0.4, 0.6, 0.8, 1.0]
  },
  "secondary":
  {
    "name": "_jetPtSubLeading",
    "variable": "_jetPtSubLeading",
    "nbins": "3",
    "xlow": "25.0",
    "xhigh": "200.0",
    "axtitle": "Subleading jet p_{T}",
    "shorttitle": "p_{T}(jet_{2})",
    "unit": "GeV",
    "bins": [25.0, 100.0, 150.0, 200.0]
  }
},
{ "name": "_eventBDTjetEtaSubLeading",
  "primary":
  {
    "name": "_eventBDT",
    "variable": "_eventBDT",
    "nbins": "5",
    "xlow": "0.0",
    "xhigh": "1.0",
    "axtitle": "BDT output score",
    "bins": [0.0, 0.2, 0.4, 0.6, 0.8, 1.0]
  },
  "secondary":
  {
    "name": "_jetEtaSubLeading",
    "variable": "_jetEtaSubLeading",
    "nbins": "4",
    "xlow": "-2.5",
    "xhigh": "2.5",
    "axtitle": "Subleading jet #eta",
    "shorttitle": "#eta(jet_{2})",
    "bins": [-2.5, -0.5, 0.0, 0.5, 2.5]
  }
},
{ "name": "_eventBDTjetAbsEtaSubLeading",
  "primary":
  {
    "name": "_eventBDT",
    "variable": "_eventBDT",
    "nbins": "5",
    "xlow": "0.0",
    "xhigh": "1.0",
    "axtitle": "BDT output score",
    "bins": [0.0, 0.2, 0.4, 0.6, 0.8, 1.0]
  },
  "secondary":
  {
    "name": "_jetAbsEtaSubLeading",
    "variable": "_jetAbsEtaSubLeading",
    "nbins": "4",
    "xlow": "0.0",
    "xhigh": "2.5",
    "axtitle": "Subleading jet |#eta|",
    "shorttitle": "|#eta(jet_{2})|",
    "bins": [0.0, 0.5, 1.0, 1.5, 2.5]
  }
},
{ "name": "_eventBDTbjetPtLeading",
  "primary":
  {
    "name": "_eventBDT",
    "variable": "_eventBDT",
    "nbins": "5",
    "xlow": "0.0",
    "xhigh": "1.0",
    "axtitle": "BDT output score",
    "bins": [0.0, 0.2, 0.4, 0.6, 0.8, 1.0]
  },
  "secondary":
  {
    "name": "_bjetPtLeading",
    "variable": "_bjetPtLeading",
    "nbins": "3",
    "xlow": "25.0",
    "xhigh": "200.0",
    "axtitle": "Leading b-tagged jet p_{T}",
    "shorttitle": "p_{T}(bjet_{1})",
    "unit": "GeV",
    "bins": [25.0, 100.0, 150.0, 200.0]
  }
},
{ "name": "_eventBDTbjetEtaLeading",
  "primary":
  {
    "name": "_eventBDT",
    "variable": "_eventBDT",
    "nbins": "5",
    "xlow": "0.0",
    "xhigh": "1.0",
    "axtitle": "BDT output score",
    "bins": [0.0, 0.2, 0.4, 0.6, 0.8, 1.0]
  },
  "secondary":
  {
    "name": "_bjetEtaLeading",
    "variable": "_bjetEtaLeading",
    "nbins": "4",
    "xlow": "-2.5",
    "xhigh": "2.5",
    "axtitle": "Leading b-tagged jet #eta",
    "shorttitle": "#eta(bjet_{1})",
    "bins": [-2.5, -0.5, 0.0, 0.5, 2.5]
  }
},
{ "name": "_eventBDTbjetAbsEtaLeading",
  "primary":
  {
    "name": "_eventBDT",
    "variable": "_eventBDT",
    "nbins": "5",
    "xlow": "0.0",
    "xhigh": "1.0",
    "axtitle": "BDT output score",
    "bins": [0.0, 0.2, 0.4, 0.6, 0.8, 1.0]
  },
  "secondary":
  {
    "name": "_bjetAbsEtaLeading",
    "variable": "_bjetAbsEtaLeading",
    "nbins": "4",
    "xlow": "0.0",
    "xhigh": "2.5",
    "axtitle": "Leading b-tagged jet |#eta|",
    "shorttitle": "|#eta(bjet_{1})|",
    "bins": [0.0, 0.5, 1.0, 1.5, 2.5]
  }
},
{ "name": "_eventBDTdRl1jet",
  "primary":
  {
    "name": "_eventBDT",
    "variable": "_eventBDT",
    "nbins": "5",
    "xlow": "0.0",
    "xhigh": "1.0",
    "axtitle": "BDT output score",
    "bins": [0.0, 0.2, 0.4, 0.6, 0.8, 1.0]
  },
  "secondary":
  {
    "name": "_dRl1jet",
    "variable": "_dRl1jet",
    "nbins": "4",
    "xlow": "0.0",
    "xhigh": "3.0",
    "axtitle": "#Delta R (l_{1} , jet)",
    "shorttitle": "#Delta R (l_{1} , jet)",
    "bins": [0.0, 1.0, 1.5, 2.0, 3.0]
  }
},
{ "name": "_eventBDTdRl1l2",
  "primary":
  {
    "name": "_eventBDT",
    "variable": "_eventBDT",
    "nbins": "5",
    "xlow": "0.0",
    "xhigh": "1.0",
    "axtitle": "BDT output score",
    "bins": [0.0, 0.2, 0.4, 0.6, 0.8, 1.0]
  },
  "secondary":
  {
    "name": "_dRl1l2",
    "variable": "_dRl1l2",
    "nbins": "4",
    "xlow": "0.0",
    "xhigh": "5.0",
    "axtitle": "#Delta R (l_{1} , l_{2})",
    "shorttitle": "#Delta R (l_{1} , l_{2})",
    "bins": [0.0, 1.5, 2.5, 3.5, 5.0]
  }
},
{ "name": "_eventBDTleptonMaxEta",
  "primary":
  {
    "name": "_eventBDT",
    "variable": "_eventBDT",
    "nbins": "5",
    "xlow": "0.0",
    "xhigh": "1.0",
    "axtitle": "BDT output score",
    "bins": [0.0, 0.2, 0.4, 0.6, 0.8, 1.0]
  },
  "secondary":
  {
    "name": "_leptonMaxEta",
    "variable": "_leptonMaxEta",
    "nbins": "4",
    "xlow": "0.0",
    "xhigh": "2.5",
    "axtitle": "Lepton maximum pseudorapidity (abs)",
    "shorttitle": "|#eta(l)_{max}|",
    "bins": [0.0, 0.75, 1.5, 2.0, 2.5]
  }
},
{ "name": "_eventBDTHT",
  "primary":
  {
    "name": "_eventBDT",
    "variable": "_eventBDT",
    "nbins": "5",
    "xlow": "0.0",
    "xhigh": "1.0",
    "axtitle": "BDT output score",
    "bins": [0.0, 0.2, 0.4, 0.6, 0.8, 1.0]
  },
  "secondary":
  {
    "name": "_HT",
    "variable": "_HT",
    "nbins": "4",
    "xlow": "0.0",
    "xhigh": "1000.0",
    "axtitle": "H_{T}",
    "shorttitle": "H_{T}",
    "unit": "GeV",
    "bins": [0.0, 200.0, 400.0, 600.0, 1000.0]
  }
}
]
